pydatalysis/.DS_Store
pydatalysis/__init__.py
pydatalysis/add.py
pydatalysis/linear_regression.py
pydatalysis/logistic_regression.py
pydatalysis-0.1.821.dist-info/METADATA
pydatalysis-0.1.821.dist-info/WHEEL
pydatalysis-0.1.821.dist-info/licenses/LICENSE
pydatalysis-0.1.821.dist-info/RECORD
