Metadata-Version: 2.1
Name: pydatalysis
Version: 0.1.821
Summary: A Python package for performing various statistical analyses
Project-URL: Homepage, https://github.com/hashimputhiyakath/pydatalysis
Project-URL: Bug Tracker, https://github.com/hashimputhiyakath/pydatalysis/issues
Author-email: Hashim Puthiyakath <hashputhiyakath@gmail.com>
License: MIT License
License-File: LICENSE
Classifier: License :: OSI Approved :: MIT License
Classifier: Operating System :: OS Independent
Classifier: Programming Language :: Python :: 3
Requires-Python: >=3.7
Requires-Dist: numpy
Requires-Dist: pandas
Requires-Dist: pingouin
Requires-Dist: statsmodels
